{
  "id": "map_sector_mixed",
  "name": "River Delta v2",
  "width": 16,
  "height": 12,
  "cellSize": 48,
  "winCondition": {
    "type": "eliminate"
  },
  "terrain": [
    [
      "cp_grass",
      "cp_grass",
      "cp_grass",
      "cp_grass",
      "cp_grass",
      "cp_grass",
      "cp_grass",
      "cp_grass",
      "cp_grass",
      "cp_grass",
      "cp_grass",
      "cp_grass",
      "cp_grass",
      "cp_grass",
      "cp_grass",
      "cp_grass"
    ],
    [
      "cp_grass",
      "cp_grass",
      "cp_grass",
      "cp_grass",
      "cp_grass",
      "cp_grass",
      "cp_grass",
      "cp_grass",
      "cp_grass",
      "cp_grass",
      "cp_grass",
      "cp_grass",
      "cp_grass",
      "cp_grass",
      "cp_grass",
      "cp_grass"
    ],
    [
      "cp_grass",
      "cp_grass",
      "cp_grass",
      "cp_grass",
      "cp_grass",
      "cp_grass",
      "cp_grass",
      "cp_grass",
      "cp_grass",
      "cp_grass",
      "cp_grass",
      "cp_grass",
      "cp_grass",
      "cp_grass",
      "cp_grass",
      "cp_grass"
    ],
    [
      "cp_grass",
      "cp_grass",
      "cp_grass",
      "cp_grass",
      "cp_grass",
      "cp_grass",
      "cp_grass",
      "cp_grass",
      "cp_grass",
      "cp_grass",
      "cp_grass",
      "cp_grass",
      "cp_grass",
      "cp_grass",
      "cp_grass",
      "cp_grass"
    ],
    [
      "cp_grass",
      "cp_grass",
      "cp_grass",
      "cp_grass",
      "cp_grass",
      "cp_grass",
      "cp_grass",
      "cp_grass",
      "cp_grass",
      "cp_grass",
      "cp_grass",
      "cp_grass",
      "cp_grass",
      "cp_grass",
      "cp_grass",
      "cp_grass"
    ],
    [
      "cp_grass",
      "cp_grass",
      "cp_grass",
      "cp_grass",
      "cp_grass",
      "cp_grass",
      "cp_grass",
      "cp_grass",
      "cp_grass",
      "cp_grass",
      "cp_grass",
      "cp_grass",
      "cp_grass",
      "cp_grass",
      "cp_grass",
      "cp_grass"
    ],
    [
      "cp_grass",
      "water",
      "water",
      "water",
      "water",
      "water",
      "water",
      "cp_grass",
      "water",
      "water",
      "water",
      "water",
      "water",
      "water",
      "water",
      "cp_grass"
    ],
    [
      "cp_grass",
      "cp_grass",
      "cp_grass",
      "building_block",
      "building_block",
      "cp_grass",
      "cp_grass",
      "cp_grass",
      "cp_grass",
      "cp_grass",
      "cp_grass",
      "cp_grass",
      "cp_grass",
      "cp_grass",
      "cp_grass",
      "cp_grass"
    ],
    [
      "cp_grass",
      "cp_grass",
      "cp_grass",
      "building_block",
      "building_block",
      "cp_grass",
      "cp_grass",
      "cp_grass",
      "cp_grass",
      "cp_grass",
      "cp_grass",
      "cp_grass",
      "cp_grass",
      "cp_grass",
      "cp_grass",
      "cp_grass"
    ],
    [
      "cp_grass",
      "cp_grass",
      "cp_grass",
      "cp_road",
      "cp_grass",
      "cp_grass",
      "cp_grass",
      "cp_grass",
      "cp_grass",
      "cp_grass",
      "cp_grass",
      "cp_grass",
      "cp_grass",
      "cp_grass",
      "cp_grass",
      "cp_grass"
    ],
    [
      "cp_grass",
      "cp_grass",
      "cp_grass",
      "cp_grass",
      "cp_grass",
      "cp_grass",
      "cp_grass",
      "cp_grass",
      "cp_grass",
      "cp_grass",
      "cp_grass",
      "cp_grass",
      "cp_grass",
      "cp_grass",
      "cp_grass",
      "cp_grass"
    ],
    [
      "cp_grass",
      "cp_grass",
      "cp_grass",
      "cp_grass",
      "cp_grass",
      "cp_grass",
      "cp_grass",
      "cp_grass",
      "cp_grass",
      "cp_grass",
      "cp_grass",
      "cp_grass",
      "cp_grass",
      "cp_grass",
      "cp_grass",
      "cp_grass"
    ]
  ],
  "units": [],
  "presetEnemies": [
    {
      "templateId": "grunt_red",
      "owner": 1,
      "x": 14,
      "y": 3
    },
    {
      "templateId": "grunt_red",
      "owner": 1,
      "x": 14,
      "y": 5
    },
    {
      "templateId": "grunt_red",
      "owner": 1,
      "x": 14,
      "y": 8
    },
    {
      "templateId": "opfor_tank",
      "owner": 1,
      "x": 15,
      "y": 5
    },
    {
      "templateId": "opfor_tank",
      "owner": 1,
      "x": 15,
      "y": 7
    }
  ],
  "skirmishDeploy": [
    {
      "x": 0,
      "y": 0
    },
    {
      "x": 0,
      "y": 1
    },
    {
      "x": 0,
      "y": 2
    },
    {
      "x": 0,
      "y": 3
    },
    {
      "x": 0,
      "y": 4
    },
    {
      "x": 0,
      "y": 5
    },
    {
      "x": 0,
      "y": 6
    },
    {
      "x": 0,
      "y": 7
    }
  ],
  "p1DeploymentSlots": [
    {
      "x": 0,
      "y": 0
    },
    {
      "x": 0,
      "y": 1
    },
    {
      "x": 0,
      "y": 2
    },
    {
      "x": 0,
      "y": 3
    },
    {
      "x": 0,
      "y": 4
    },
    {
      "x": 0,
      "y": 5
    },
    {
      "x": 0,
      "y": 6
    },
    {
      "x": 0,
      "y": 7
    }
  ],
  "p2DeploymentSlots": [
    {
      "x": 15,
      "y": 0
    },
    {
      "x": 15,
      "y": 1
    },
    {
      "x": 15,
      "y": 2
    },
    {
      "x": 15,
      "y": 3
    },
    {
      "x": 15,
      "y": 4
    },
    {
      "x": 15,
      "y": 5
    },
    {
      "x": 15,
      "y": 6
    },
    {
      "x": 15,
      "y": 7
    }
  ],
  "mapObjects": [
    {
      "id": "obj_7_5_yoe6w",
      "x": 7,
      "y": 5,
      "sprite": "assets/obstacles/urban/Obstacle_Urban_Prop_68f47d7c.png",
      "visualKind": "crate",
      "blocksMove": true,
      "blocksLos": true
    },
    {
      "id": "obj_5_7_6389i",
      "x": 5,
      "y": 7,
      "sprite": "assets/obstacles/urban/Obstacle_Urban_Prop_9c85a7ed.png",
      "visualKind": "crate",
      "blocksMove": true,
      "blocksLos": true
    },
    {
      "id": "obj_6_8_tbj23",
      "x": 6,
      "y": 8,
      "sprite": "assets/obstacles/urban/Obstacle_Urban_Prop_6524b622.png",
      "visualKind": "crate",
      "blocksMove": true,
      "blocksLos": true
    },
    {
      "id": "obj_10_9_k21u4",
      "x": 10,
      "y": 9,
      "sprite": "assets/obstacles/urban/Obstacle_Urban_Strip_d81af864.png",
      "visualKind": "strip",
      "blocksMove": true,
      "blocksLos": true
    },
    {
      "id": "obj_2_5_1oc8o",
      "x": 2,
      "y": 5,
      "sprite": "assets/obstacles/urban/Obstacle_Urban_Strip_3ef9a1b8.png",
      "visualKind": "strip",
      "blocksMove": true,
      "blocksLos": true
    },
    {
      "id": "obj_10_5_3e5l2",
      "x": 10,
      "y": 5,
      "sprite": "assets/obstacles/urban/Obstacle_Urban_Prop_3278bfec.png",
      "visualKind": "crate",
      "blocksMove": true,
      "blocksLos": true
    },
    {
      "id": "obj_10_10_69rvo",
      "x": 10,
      "y": 10,
      "sprite": "assets/obstacles/urban/Obstacle_Urban_Prop_38a709a5.png",
      "visualKind": "crate",
      "blocksMove": true,
      "blocksLos": true
    },
    {
      "id": "obj_5_9_538dg",
      "x": 5,
      "y": 9,
      "sprite": "assets/obstacles/urban/Obstacle_Urban_Prop_14d8ec31.png",
      "visualKind": "crate",
      "blocksMove": true,
      "blocksLos": true
    },
    {
      "id": "obj_4_10_u8i4g",
      "x": 4,
      "y": 10,
      "sprite": "assets/obstacles/urban/Obstacle_Urban_Prop_95096f7f.png",
      "visualKind": "crate",
      "blocksMove": true,
      "blocksLos": true
    },
    {
      "id": "obj_7_10_omeiy",
      "x": 7,
      "y": 10,
      "sprite": "assets/obstacles/urban/Obstacle_Urban_Prop_b238d5ef.png",
      "visualKind": "crate",
      "blocksMove": true,
      "blocksLos": true
    },
    {
      "id": "obj_7_4_oq04w",
      "x": 7,
      "y": 4,
      "sprite": "assets/obstacles/urban/Obstacle_Urban_Strip_3ef9a1b8.png",
      "visualKind": "strip",
      "blocksMove": true,
      "blocksLos": true
    },
    {
      "id": "obj_14_7_g5uas",
      "x": 14,
      "y": 7,
      "sprite": "assets/obstacles/urban/Obstacle_Urban_Prop_14d8ec31.png",
      "visualKind": "crate",
      "blocksMove": true,
      "blocksLos": true
    },
    {
      "id": "obj_9_10_bye2t",
      "x": 9,
      "y": 10,
      "sprite": "assets/obstacles/urban/Obstacle_Urban_Prop_6524b622.png",
      "visualKind": "crate",
      "blocksMove": true,
      "blocksLos": true
    },
    {
      "id": "obj_11_8_ysgs4",
      "x": 11,
      "y": 8,
      "sprite": "assets/obstacles/urban/Obstacle_Urban_Prop_14d8ec31.png",
      "visualKind": "crate",
      "blocksMove": true,
      "blocksLos": true
    },
    {
      "id": "obj_12_8_c0d9l",
      "x": 12,
      "y": 8,
      "sprite": "assets/obstacles/urban/Obstacle_Urban_Strip_3ef9a1b8.png",
      "visualKind": "strip",
      "blocksMove": true,
      "blocksLos": true
    },
    {
      "id": "obj_9_5_ugo14",
      "x": 9,
      "y": 5,
      "sprite": "assets/obstacles/urban/Obstacle_Urban_Prop_786c0f3a.png",
      "visualKind": "crate",
      "blocksMove": true,
      "blocksLos": true
    }
  ],
  "buildings": [
    {
      "id": "bld_3_7",
      "footprint": [
        {
          "x": 3,
          "y": 7
        },
        {
          "x": 4,
          "y": 7
        },
        {
          "x": 3,
          "y": 8
        },
        {
          "x": 4,
          "y": 8
        }
      ],
      "entry": {
        "x": 3,
        "y": 9
      },
      "facadeSprite": "assets/buildings/medium/Building_Urban_Medium_9c86ff08.png",
      "interiorProps": []
    }
  ],
  "generator": {
    "version": 1,
    "seed": 1308939435,
    "theme": "urban",
    "dividerConnectorCount": 0,
    "flowConnectors": [
      {
        "x": 1,
        "y": 6,
        "terrainId": "water",
        "mask": 2,
        "variant": "end_e",
        "spritePath": "assets/tiles/urban/Tile_Urban_WaterStrip_64d87f88.png",
        "spriteSheetFrame": 2
      },
      {
        "x": 2,
        "y": 6,
        "terrainId": "water",
        "mask": 10,
        "variant": "straight_ew",
        "spritePath": "assets/tiles/urban/Tile_Urban_WaterStrip_64d87f88.png",
        "spriteSheetFrame": 3
      },
      {
        "x": 3,
        "y": 6,
        "terrainId": "water",
        "mask": 10,
        "variant": "straight_ew",
        "spritePath": "assets/tiles/urban/Tile_Urban_WaterStrip_64d87f88.png",
        "spriteSheetFrame": 3
      },
      {
        "x": 4,
        "y": 6,
        "terrainId": "water",
        "mask": 10,
        "variant": "straight_ew",
        "spritePath": "assets/tiles/urban/Tile_Urban_WaterStrip_64d87f88.png",
        "spriteSheetFrame": 3
      },
      {
        "x": 5,
        "y": 6,
        "terrainId": "water",
        "mask": 10,
        "variant": "straight_ew",
        "spritePath": "assets/tiles/urban/Tile_Urban_WaterStrip_64d87f88.png",
        "spriteSheetFrame": 3
      },
      {
        "x": 6,
        "y": 6,
        "terrainId": "water",
        "mask": 8,
        "variant": "end_w",
        "spritePath": "assets/tiles/urban/Tile_Urban_WaterStrip_64d87f88.png",
        "spriteSheetFrame": 3
      },
      {
        "x": 8,
        "y": 6,
        "terrainId": "water",
        "mask": 2,
        "variant": "end_e",
        "spritePath": "assets/tiles/urban/Tile_Urban_WaterStrip_64d87f88.png",
        "spriteSheetFrame": 2
      },
      {
        "x": 9,
        "y": 6,
        "terrainId": "water",
        "mask": 10,
        "variant": "straight_ew",
        "spritePath": "assets/tiles/urban/Tile_Urban_WaterStrip_64d87f88.png",
        "spriteSheetFrame": 3
      },
      {
        "x": 10,
        "y": 6,
        "terrainId": "water",
        "mask": 10,
        "variant": "straight_ew",
        "spritePath": "assets/tiles/urban/Tile_Urban_WaterStrip_64d87f88.png",
        "spriteSheetFrame": 3
      },
      {
        "x": 11,
        "y": 6,
        "terrainId": "water",
        "mask": 10,
        "variant": "straight_ew",
        "spritePath": "assets/tiles/urban/Tile_Urban_WaterStrip_64d87f88.png",
        "spriteSheetFrame": 3
      },
      {
        "x": 12,
        "y": 6,
        "terrainId": "water",
        "mask": 10,
        "variant": "straight_ew",
        "spritePath": "assets/tiles/urban/Tile_Urban_WaterStrip_64d87f88.png",
        "spriteSheetFrame": 3
      },
      {
        "x": 13,
        "y": 6,
        "terrainId": "water",
        "mask": 10,
        "variant": "straight_ew",
        "spritePath": "assets/tiles/urban/Tile_Urban_WaterStrip_64d87f88.png",
        "spriteSheetFrame": 3
      },
      {
        "x": 14,
        "y": 6,
        "terrainId": "water",
        "mask": 8,
        "variant": "end_w",
        "spritePath": "assets/tiles/urban/Tile_Urban_WaterStrip_64d87f88.png",
        "spriteSheetFrame": 3
      },
      {
        "x": 3,
        "y": 9,
        "terrainId": "cp_road",
        "mask": 0,
        "variant": "isolated",
        "spritePath": null,
        "spriteSheetFrame": 0
      }
    ],
    "migration": {
      "tool": "migrate_maps.mjs",
      "catalogId": "map_sector_mixed",
      "migratedAt": "2026-04-04T20:31:52.624Z",
      "environment": "mixed",
      "preservedPresetCount": 5
    }
  },
  "fogOfWar": false,
  "ambientEffects": [
    {
      "x": 6,
      "y": 6,
      "spritePath": "assets/tiles/urban/fire_animation.png",
      "frameCount": 8,
      "fps": 10
    },
    {
      "x": 10,
      "y": 6,
      "spritePath": "assets/tiles/urban/fire_animation2.png",
      "frameCount": 8,
      "fps": 9
    }
  ]
}
