{
  "tournament": {
    "title": "Season Signup",
    "blurb": "Brackets stubbed",
    "externalUrl": "https://example.com/ctu-tournament-signup",
    "buttonLabel": "Signup"
  },
  "soloModes": [
    {
      "id": "procedural_skirmish",
      "title": "Procedural skirmish (urban)",
      "description": "Random 16×12 urban map: river, fords, two flanking routes, buildings, and CraftPix props.",
      "action": "procedural",
      "procTheme": "urban",
      "iconKey": "maps",
      "requiresAcademy": false
    },
    {
      "id": "procedural_skirmish_desert",
      "title": "Procedural skirmish (desert)",
      "description": "Random 16×12 desert map: oasis channel, fords, dunes, and theme props (no urban building footprints).",
      "action": "procedural",
      "procTheme": "desert",
      "iconKey": "maps",
      "requiresAcademy": false
    },
    {
      "id": "plane_layer_lab",
      "title": "Battle mat lab",
      "description": "Pick mat surface (grass / desert / urban), choose 1–8 units, then fight on the plane-over-grid stack with dense props.",
      "action": "mat_lab",
      "iconKey": "maps",
      "requiresAcademy": false
    },
    {
      "id": "map_theater",
      "title": "Map theater",
      "description": "Pick one of 20 battlefields for skirmish or hotseat.",
      "action": "maps",
      "iconKey": "maps",
      "requiresAcademy": false
    },
    {
      "id": "academy",
      "title": "Training Academy",
      "description": "Pick 3 units — forest LOS, flanking encouraged.",
      "action": "academy",
      "iconKey": "academy",
      "requiresAcademy": false
    },
    {
      "id": "trial_survive",
      "title": "Trial: Defend",
      "description": "Survive 4 rounds. Hills and urban sap sight.",
      "action": "trial",
      "iconKey": "defend",
      "bullet": true,
      "scenarioPath": "js/config/scenarios/trial_survive.json",
      "requiresAcademy": false
    },
    {
      "id": "skirmish",
      "title": "Vs CPU (setup)",
      "description": "Choose your map and squad in any order, then start the battle.",
      "action": "skirmish",
      "iconKey": "skirmish",
      "requiresAcademy": false
    },
    {
      "id": "target_ai",
      "title": "Target: AI Engaged",
      "description": "Asymmetric AI encounter — survive contact and counterattack.",
      "action": "skirmish",
      "iconKey": "target",
      "bullet": true,
      "requiresAcademy": true
    },
    {
      "id": "urban_assault",
      "title": "Urban Assault",
      "description": "City streets, tight corridors, restricted LOS.",
      "action": "scenario",
      "iconKey": "urban",
      "scenarioPath": "js/config/scenarios/urban_assault.json",
      "requiresAcademy": true
    },
    {
      "id": "river_crossing",
      "title": "River Crossing",
      "description": "Two bridges, one river. Control the crossings.",
      "action": "scenario",
      "iconKey": "river",
      "scenarioPath": "js/config/scenarios/river_crossing.json",
      "requiresAcademy": true
    }
  ],
  "shortcuts": [
    { "label": "Map theater", "icon": "🗺", "screen": "maps",     "requiresAcademy": false },
    { "label": "Unit Codex",  "icon": "📖", "screen": "codex",    "requiresAcademy": false },
    { "label": "1v1 Hotseat", "icon": "⚔",  "screen": "hotseat",  "requiresAcademy": true  },
    { "label": "Settings",    "icon": "⚙",  "screen": "settings", "requiresAcademy": false }
  ]
}
